pyraxial/__init__.py
pyraxial/__init__.py.old
pyraxial-0.2.6b0.dist-info/WHEEL
pyraxial-0.2.6b0.dist-info/METADATA
pyraxial-0.2.6b0.dist-info/LICENSE
pyraxial-0.2.6b0.dist-info/RECORD
