Metadata-Version: 2.1
Name: pyraxial
Version: 0.2.6-beta
Summary: An algebraic take on axis-aligned rectangles.
License: MIT
Keywords: bounding-box
Author-email: Mick Krippendorf <m.krippendorf@freenet.de>
Requires-Python: >=3.7
Classifier: Development Status :: 4 - Beta
Classifier: Intended Audience :: Developers
Classifier: License :: OSI Approved :: MIT License
Classifier: Operating System :: OS Independent
Classifier: Programming Language :: Python :: 3
Classifier: Programming Language :: Python :: 3.10
Classifier: Programming Language :: Python :: 3.7
Classifier: Programming Language :: Python :: 3.8
Classifier: Programming Language :: Python :: 3.9
Classifier: Topic :: Software Development :: Libraries :: Python Modules
Requires-Dist: itree~=0.0
Project-URL: documentation, https://pillmuncher.github.io/pyraxial
Project-URL: homepage, https://pillmuncher.github.io/pyraxial
Project-URL: repository, https://github.com/pillmuncher/pyraxial
